pdg_mp3_converter/__init__.py
pdg_mp3_converter/converter.py
pdg_mp3_converter-0.0.2.dist-info/LICENSE
pdg_mp3_converter-0.0.2.dist-info/METADATA
pdg_mp3_converter-0.0.2.dist-info/WHEEL
pdg_mp3_converter-0.0.2.dist-info/top_level.txt
pdg_mp3_converter-0.0.2.dist-info/RECORD
