Metadata-Version: 2.1
Name: pdg-mp3-converter
Version: 0.0.2
Summary: For converting mp4 files to mp3 and also mp3 files back to mp4
Home-page: https://github.com/PaulusDeGross/pdg-mp3-converter
Author: Paul Maerz
Author-email: maerzpaul06@gmail.com
License: UNKNOWN
Platform: UNKNOWN
Classifier: Programming Language :: Python :: 3
Classifier: License :: OSI Approved :: MIT License
Classifier: Operating System :: OS Independent
Requires-Python: >=3.9
License-File: LICENSE
